[
  {
    "cpu_time_seconds": 58.761191999999994,
    "device_memory_current_bytes": 173368064,
    "device_memory_peak_bytes": 173368064,
    "device_memory_reserved_current_bytes": 583057408,
    "device_memory_reserved_peak_bytes": 583057408,
    "device_type": "mps",
    "epoch": 1,
    "ram_current_bytes_end": 1500430336,
    "ram_current_bytes_start": 438009856,
    "ram_peak_bytes_end": 1500463104,
    "wall_time_seconds": 91.16562041699945
  },
  {
    "cpu_time_seconds": 56.97633199999999,
    "device_memory_current_bytes": 174733824,
    "device_memory_peak_bytes": 174733824,
    "device_memory_reserved_current_bytes": 583057408,
    "device_memory_reserved_peak_bytes": 583057408,
    "device_type": "mps",
    "epoch": 2,
    "ram_current_bytes_end": 1513013248,
    "ram_current_bytes_start": 1502019584,
    "ram_peak_bytes_end": 1513046016,
    "wall_time_seconds": 81.95487066700116
  },
  {
    "cpu_time_seconds": 57.688351,
    "device_memory_current_bytes": 174733824,
    "device_memory_peak_bytes": 174733824,
    "device_memory_reserved_current_bytes": 583057408,
    "device_memory_reserved_peak_bytes": 583057408,
    "device_type": "mps",
    "epoch": 3,
    "ram_current_bytes_end": 1514766336,
    "ram_current_bytes_start": 1513144320,
    "ram_peak_bytes_end": 1514799104,
    "wall_time_seconds": 82.77176624999993
  },
  {
    "cpu_time_seconds": 57.787743000000006,
    "device_memory_current_bytes": 174733824,
    "device_memory_peak_bytes": 174733824,
    "device_memory_reserved_current_bytes": 583057408,
    "device_memory_reserved_peak_bytes": 583057408,
    "device_type": "mps",
    "epoch": 4,
    "ram_current_bytes_end": 1516306432,
    "ram_current_bytes_start": 1514930176,
    "ram_peak_bytes_end": 1516355584,
    "wall_time_seconds": 82.0839361670005
  },
  {
    "cpu_time_seconds": 57.754268999999965,
    "device_memory_current_bytes": 174733824,
    "device_memory_peak_bytes": 174733824,
    "device_memory_reserved_current_bytes": 583057408,
    "device_memory_reserved_peak_bytes": 583057408,
    "device_type": "mps",
    "epoch": 5,
    "ram_current_bytes_end": 1517764608,
    "ram_current_bytes_start": 1516421120,
    "ram_peak_bytes_end": 1517797376,
    "wall_time_seconds": 81.61936179099939
  },
  {
    "cpu_time_seconds": 58.099797000000024,
    "device_memory_current_bytes": 174733824,
    "device_memory_peak_bytes": 174733824,
    "device_memory_reserved_current_bytes": 583057408,
    "device_memory_reserved_peak_bytes": 583057408,
    "device_type": "mps",
    "epoch": 6,
    "ram_current_bytes_end": 1519255552,
    "ram_current_bytes_start": 1517895680,
    "ram_peak_bytes_end": 1519288320,
    "wall_time_seconds": 81.66074329200092
  },
  {
    "cpu_time_seconds": 58.65778,
    "device_memory_current_bytes": 174733824,
    "device_memory_peak_bytes": 174733824,
    "device_memory_reserved_current_bytes": 583057408,
    "device_memory_reserved_peak_bytes": 583057408,
    "device_type": "mps",
    "epoch": 7,
    "ram_current_bytes_end": 1520828416,
    "ram_current_bytes_start": 1519419392,
    "ram_peak_bytes_end": 1520861184,
    "wall_time_seconds": 81.70564691599975
  },
  {
    "cpu_time_seconds": 58.463798999999995,
    "device_memory_current_bytes": 174733824,
    "device_memory_peak_bytes": 174733824,
    "device_memory_reserved_current_bytes": 583057408,
    "device_memory_reserved_peak_bytes": 583057408,
    "device_type": "mps",
    "epoch": 8,
    "ram_current_bytes_end": 1522155520,
    "ram_current_bytes_start": 1520943104,
    "ram_peak_bytes_end": 1522188288,
    "wall_time_seconds": 81.66637412500131
  },
  {
    "cpu_time_seconds": 58.571146999999996,
    "device_memory_current_bytes": 174733824,
    "device_memory_peak_bytes": 174733824,
    "device_memory_reserved_current_bytes": 583057408,
    "device_memory_reserved_peak_bytes": 583057408,
    "device_type": "mps",
    "epoch": 9,
    "ram_current_bytes_end": 1523499008,
    "ram_current_bytes_start": 1522270208,
    "ram_peak_bytes_end": 1523531776,
    "wall_time_seconds": 81.68599320799876
  },
  {
    "cpu_time_seconds": 59.36843899999997,
    "device_memory_current_bytes": 174733824,
    "device_memory_peak_bytes": 174733824,
    "device_memory_reserved_current_bytes": 583057408,
    "device_memory_reserved_peak_bytes": 583057408,
    "device_type": "mps",
    "epoch": 10,
    "ram_current_bytes_end": 1525022720,
    "ram_current_bytes_start": 1523630080,
    "ram_peak_bytes_end": 1525071872,
    "wall_time_seconds": 81.10772991699923
  },
  {
    "cpu_time_seconds": 58.984797999999955,
    "device_memory_current_bytes": 174733824,
    "device_memory_peak_bytes": 174733824,
    "device_memory_reserved_current_bytes": 583057408,
    "device_memory_reserved_peak_bytes": 583057408,
    "device_type": "mps",
    "epoch": 11,
    "ram_current_bytes_end": 1526284288,
    "ram_current_bytes_start": 1525137408,
    "ram_peak_bytes_end": 1526317056,
    "wall_time_seconds": 79.46459529200001
  },
  {
    "cpu_time_seconds": 58.61898499999995,
    "device_memory_current_bytes": 174733824,
    "device_memory_peak_bytes": 174733824,
    "device_memory_reserved_current_bytes": 583057408,
    "device_memory_reserved_peak_bytes": 583057408,
    "device_type": "mps",
    "epoch": 12,
    "ram_current_bytes_end": 1527562240,
    "ram_current_bytes_start": 1526415360,
    "ram_peak_bytes_end": 1527627776,
    "wall_time_seconds": 79.50031762500112
  },
  {
    "cpu_time_seconds": 57.636653000000024,
    "device_memory_current_bytes": 174733824,
    "device_memory_peak_bytes": 174733824,
    "device_memory_reserved_current_bytes": 583057408,
    "device_memory_reserved_peak_bytes": 583057408,
    "device_type": "mps",
    "epoch": 13,
    "ram_current_bytes_end": 1528938496,
    "ram_current_bytes_start": 1527726080,
    "ram_peak_bytes_end": 1529004032,
    "wall_time_seconds": 79.39711524999984
  },
  {
    "cpu_time_seconds": 57.680565,
    "device_memory_current_bytes": 174733824,
    "device_memory_peak_bytes": 174733824,
    "device_memory_reserved_current_bytes": 583057408,
    "device_memory_reserved_peak_bytes": 583057408,
    "device_type": "mps",
    "epoch": 14,
    "ram_current_bytes_end": 1530314752,
    "ram_current_bytes_start": 1529069568,
    "ram_peak_bytes_end": 1530363904,
    "wall_time_seconds": 79.37181099999907
  },
  {
    "cpu_time_seconds": 57.83921399999997,
    "device_memory_current_bytes": 174733824,
    "device_memory_peak_bytes": 174733824,
    "device_memory_reserved_current_bytes": 583057408,
    "device_memory_reserved_peak_bytes": 583057408,
    "device_type": "mps",
    "epoch": 15,
    "ram_current_bytes_end": 1531641856,
    "ram_current_bytes_start": 1530445824,
    "ram_peak_bytes_end": 1531707392,
    "wall_time_seconds": 79.3754949590002
  },
  {
    "cpu_time_seconds": 57.496136999999976,
    "device_memory_current_bytes": 174733824,
    "device_memory_peak_bytes": 174733824,
    "device_memory_reserved_current_bytes": 583057408,
    "device_memory_reserved_peak_bytes": 583057408,
    "device_type": "mps",
    "epoch": 16,
    "ram_current_bytes_end": 1534410752,
    "ram_current_bytes_start": 1533296640,
    "ram_peak_bytes_end": 1534476288,
    "wall_time_seconds": 79.17943958299838
  },
  {
    "cpu_time_seconds": 57.58160099999998,
    "device_memory_current_bytes": 174733824,
    "device_memory_peak_bytes": 174733824,
    "device_memory_reserved_current_bytes": 583057408,
    "device_memory_reserved_peak_bytes": 583057408,
    "device_type": "mps",
    "epoch": 17,
    "ram_current_bytes_end": 1535836160,
    "ram_current_bytes_start": 1534558208,
    "ram_peak_bytes_end": 1535885312,
    "wall_time_seconds": 80.0034226250009
  },
  {
    "cpu_time_seconds": 58.671366000000035,
    "device_memory_current_bytes": 174733824,
    "device_memory_peak_bytes": 174733824,
    "device_memory_reserved_current_bytes": 583057408,
    "device_memory_reserved_peak_bytes": 583057408,
    "device_type": "mps",
    "epoch": 18,
    "ram_current_bytes_end": 1537196032,
    "ram_current_bytes_start": 1535967232,
    "ram_peak_bytes_end": 1537245184,
    "wall_time_seconds": 82.5114675420009
  }
]
