[
  {
    "cpu_time_seconds": 22.374644,
    "device_memory_current_bytes": 62711552,
    "device_memory_peak_bytes": 62711552,
    "device_memory_reserved_current_bytes": 143556608,
    "device_memory_reserved_peak_bytes": 143556608,
    "device_type": "mps",
    "epoch": 1,
    "ram_current_bytes_end": 971456512,
    "ram_current_bytes_start": 386269184,
    "ram_peak_bytes_end": 971489280,
    "wall_time_seconds": 33.64210091700079
  },
  {
    "cpu_time_seconds": 21.292040000000004,
    "device_memory_current_bytes": 62711552,
    "device_memory_peak_bytes": 62711552,
    "device_memory_reserved_current_bytes": 147750912,
    "device_memory_reserved_peak_bytes": 147750912,
    "device_type": "mps",
    "epoch": 2,
    "ram_current_bytes_end": 991739904,
    "ram_current_bytes_start": 973553664,
    "ram_peak_bytes_end": 991838208,
    "wall_time_seconds": 20.17755983400275
  },
  {
    "cpu_time_seconds": 21.243037,
    "device_memory_current_bytes": 62711552,
    "device_memory_peak_bytes": 62711552,
    "device_memory_reserved_current_bytes": 147750912,
    "device_memory_reserved_peak_bytes": 147750912,
    "device_type": "mps",
    "epoch": 3,
    "ram_current_bytes_end": 1005666304,
    "ram_current_bytes_start": 992264192,
    "ram_peak_bytes_end": 1005764608,
    "wall_time_seconds": 20.037367625016486
  },
  {
    "cpu_time_seconds": 21.281062000000006,
    "device_memory_current_bytes": 62711552,
    "device_memory_peak_bytes": 62711552,
    "device_memory_reserved_current_bytes": 147750912,
    "device_memory_reserved_peak_bytes": 147750912,
    "device_type": "mps",
    "epoch": 4,
    "ram_current_bytes_end": 1021149184,
    "ram_current_bytes_start": 1006206976,
    "ram_peak_bytes_end": 1021247488,
    "wall_time_seconds": 20.17273741698591
  },
  {
    "cpu_time_seconds": 21.281802,
    "device_memory_current_bytes": 62711552,
    "device_memory_peak_bytes": 62711552,
    "device_memory_reserved_current_bytes": 147750912,
    "device_memory_reserved_peak_bytes": 147750912,
    "device_type": "mps",
    "epoch": 5,
    "ram_current_bytes_end": 1034371072,
    "ram_current_bytes_start": 1021509632,
    "ram_peak_bytes_end": 1034469376,
    "wall_time_seconds": 20.217998000007356
  },
  {
    "cpu_time_seconds": 21.815478,
    "device_memory_current_bytes": 62711552,
    "device_memory_peak_bytes": 62711552,
    "device_memory_reserved_current_bytes": 143556608,
    "device_memory_reserved_peak_bytes": 143556608,
    "device_type": "mps",
    "epoch": 6,
    "ram_current_bytes_end": 935821312,
    "ram_current_bytes_start": 1034846208,
    "ram_peak_bytes_end": 1046216704,
    "wall_time_seconds": 21.05542554098065
  },
  {
    "cpu_time_seconds": 21.850825000000015,
    "device_memory_current_bytes": 62711552,
    "device_memory_peak_bytes": 62711552,
    "device_memory_reserved_current_bytes": 147750912,
    "device_memory_reserved_peak_bytes": 147750912,
    "device_type": "mps",
    "epoch": 7,
    "ram_current_bytes_end": 963543040,
    "ram_current_bytes_start": 945635328,
    "ram_peak_bytes_end": 1046216704,
    "wall_time_seconds": 20.644918959005736
  },
  {
    "cpu_time_seconds": 21.547968999999995,
    "device_memory_current_bytes": 62711552,
    "device_memory_peak_bytes": 62711552,
    "device_memory_reserved_current_bytes": 147750912,
    "device_memory_reserved_peak_bytes": 147750912,
    "device_type": "mps",
    "epoch": 8,
    "ram_current_bytes_end": 977076224,
    "ram_current_bytes_start": 963641344,
    "ram_peak_bytes_end": 1046216704,
    "wall_time_seconds": 20.386036666983273
  },
  {
    "cpu_time_seconds": 21.234184,
    "device_memory_current_bytes": 62711552,
    "device_memory_peak_bytes": 62711552,
    "device_memory_reserved_current_bytes": 147750912,
    "device_memory_reserved_peak_bytes": 147750912,
    "device_type": "mps",
    "epoch": 9,
    "ram_current_bytes_end": 990494720,
    "ram_current_bytes_start": 977485824,
    "ram_peak_bytes_end": 1046216704,
    "wall_time_seconds": 20.041814416996203
  },
  {
    "cpu_time_seconds": 21.14906400000001,
    "device_memory_current_bytes": 62711552,
    "device_memory_peak_bytes": 62711552,
    "device_memory_reserved_current_bytes": 147750912,
    "device_memory_reserved_peak_bytes": 147750912,
    "device_type": "mps",
    "epoch": 10,
    "ram_current_bytes_end": 1005076480,
    "ram_current_bytes_start": 992428032,
    "ram_peak_bytes_end": 1046216704,
    "wall_time_seconds": 20.074632125004428
  },
  {
    "cpu_time_seconds": 21.340925,
    "device_memory_current_bytes": 62711552,
    "device_memory_peak_bytes": 62711552,
    "device_memory_reserved_current_bytes": 147750912,
    "device_memory_reserved_peak_bytes": 147750912,
    "device_type": "mps",
    "epoch": 11,
    "ram_current_bytes_end": 1019133952,
    "ram_current_bytes_start": 1006043136,
    "ram_peak_bytes_end": 1046216704,
    "wall_time_seconds": 20.14166954101529
  },
  {
    "cpu_time_seconds": 21.298478000000017,
    "device_memory_current_bytes": 62711552,
    "device_memory_peak_bytes": 62711552,
    "device_memory_reserved_current_bytes": 147750912,
    "device_memory_reserved_peak_bytes": 147750912,
    "device_type": "mps",
    "epoch": 12,
    "ram_current_bytes_end": 1033666560,
    "ram_current_bytes_start": 1019609088,
    "ram_peak_bytes_end": 1046216704,
    "wall_time_seconds": 20.163467291975394
  },
  {
    "cpu_time_seconds": 21.095496000000026,
    "device_memory_current_bytes": 62711552,
    "device_memory_peak_bytes": 62711552,
    "device_memory_reserved_current_bytes": 147750912,
    "device_memory_reserved_peak_bytes": 147750912,
    "device_type": "mps",
    "epoch": 13,
    "ram_current_bytes_end": 1046953984,
    "ram_current_bytes_start": 1033715712,
    "ram_peak_bytes_end": 1047052288,
    "wall_time_seconds": 19.98835687499377
  },
  {
    "cpu_time_seconds": 21.296023000000048,
    "device_memory_current_bytes": 62711552,
    "device_memory_peak_bytes": 62711552,
    "device_memory_reserved_current_bytes": 147750912,
    "device_memory_reserved_peak_bytes": 147750912,
    "device_type": "mps",
    "epoch": 14,
    "ram_current_bytes_end": 1060225024,
    "ram_current_bytes_start": 1047265280,
    "ram_peak_bytes_end": 1060323328,
    "wall_time_seconds": 20.201362416002667
  },
  {
    "cpu_time_seconds": 21.312621000000036,
    "device_memory_current_bytes": 62711552,
    "device_memory_peak_bytes": 62711552,
    "device_memory_reserved_current_bytes": 147750912,
    "device_memory_reserved_peak_bytes": 147750912,
    "device_type": "mps",
    "epoch": 15,
    "ram_current_bytes_end": 1073594368,
    "ram_current_bytes_start": 1060290560,
    "ram_peak_bytes_end": 1073692672,
    "wall_time_seconds": 20.21782983400044
  },
  {
    "cpu_time_seconds": 21.42872699999998,
    "device_memory_current_bytes": 62711552,
    "device_memory_peak_bytes": 62711552,
    "device_memory_reserved_current_bytes": 147750912,
    "device_memory_reserved_peak_bytes": 147750912,
    "device_type": "mps",
    "epoch": 16,
    "ram_current_bytes_end": 1086881792,
    "ram_current_bytes_start": 1073856512,
    "ram_peak_bytes_end": 1086947328,
    "wall_time_seconds": 20.312273791991174
  },
  {
    "cpu_time_seconds": 21.281904999999995,
    "device_memory_current_bytes": 62711552,
    "device_memory_peak_bytes": 62711552,
    "device_memory_reserved_current_bytes": 147750912,
    "device_memory_reserved_peak_bytes": 147750912,
    "device_type": "mps",
    "epoch": 17,
    "ram_current_bytes_end": 1100070912,
    "ram_current_bytes_start": 1086930944,
    "ram_peak_bytes_end": 1100169216,
    "wall_time_seconds": 20.07106054201722
  },
  {
    "cpu_time_seconds": 21.282803,
    "device_memory_current_bytes": 62711552,
    "device_memory_peak_bytes": 62711552,
    "device_memory_reserved_current_bytes": 147750912,
    "device_memory_reserved_peak_bytes": 147750912,
    "device_type": "mps",
    "epoch": 18,
    "ram_current_bytes_end": 1113374720,
    "ram_current_bytes_start": 1100382208,
    "ram_peak_bytes_end": 1113473024,
    "wall_time_seconds": 20.162925959011773
  },
  {
    "cpu_time_seconds": 21.286774999999977,
    "device_memory_current_bytes": 62711552,
    "device_memory_peak_bytes": 62711552,
    "device_memory_reserved_current_bytes": 147750912,
    "device_memory_reserved_peak_bytes": 147750912,
    "device_type": "mps",
    "epoch": 19,
    "ram_current_bytes_end": 1126498304,
    "ram_current_bytes_start": 1113784320,
    "ram_peak_bytes_end": 1126596608,
    "wall_time_seconds": 20.136946124985116
  },
  {
    "cpu_time_seconds": 21.347953000000018,
    "device_memory_current_bytes": 62711552,
    "device_memory_peak_bytes": 62711552,
    "device_memory_reserved_current_bytes": 147750912,
    "device_memory_reserved_peak_bytes": 147750912,
    "device_type": "mps",
    "epoch": 20,
    "ram_current_bytes_end": 1139933184,
    "ram_current_bytes_start": 1126907904,
    "ram_peak_bytes_end": 1140031488,
    "wall_time_seconds": 20.08144008301315
  },
  {
    "cpu_time_seconds": 21.391602999999975,
    "device_memory_current_bytes": 62711552,
    "device_memory_peak_bytes": 62711552,
    "device_memory_reserved_current_bytes": 147750912,
    "device_memory_reserved_peak_bytes": 147750912,
    "device_type": "mps",
    "epoch": 21,
    "ram_current_bytes_end": 1153417216,
    "ram_current_bytes_start": 1140129792,
    "ram_peak_bytes_end": 1153515520,
    "wall_time_seconds": 20.263248540984932
  },
  {
    "cpu_time_seconds": 21.390713000000005,
    "device_memory_current_bytes": 62711552,
    "device_memory_peak_bytes": 62711552,
    "device_memory_reserved_current_bytes": 147750912,
    "device_memory_reserved_peak_bytes": 147750912,
    "device_type": "mps",
    "epoch": 22,
    "ram_current_bytes_end": 1166688256,
    "ram_current_bytes_start": 1153662976,
    "ram_peak_bytes_end": 1166786560,
    "wall_time_seconds": 20.236986791016534
  },
  {
    "cpu_time_seconds": 21.206169999999986,
    "device_memory_current_bytes": 62711552,
    "device_memory_peak_bytes": 62711552,
    "device_memory_reserved_current_bytes": 147750912,
    "device_memory_reserved_peak_bytes": 147750912,
    "device_type": "mps",
    "epoch": 23,
    "ram_current_bytes_end": 1180401664,
    "ram_current_bytes_start": 1166770176,
    "ram_peak_bytes_end": 1180499968,
    "wall_time_seconds": 20.14090845899773
  },
  {
    "cpu_time_seconds": 21.21587999999997,
    "device_memory_current_bytes": 62711552,
    "device_memory_peak_bytes": 62711552,
    "device_memory_reserved_current_bytes": 147750912,
    "device_memory_reserved_peak_bytes": 147750912,
    "device_type": "mps",
    "epoch": 24,
    "ram_current_bytes_end": 1193492480,
    "ram_current_bytes_start": 1180794880,
    "ram_peak_bytes_end": 1193574400,
    "wall_time_seconds": 20.010776542010717
  },
  {
    "cpu_time_seconds": 21.272129999999947,
    "device_memory_current_bytes": 62711552,
    "device_memory_peak_bytes": 62711552,
    "device_memory_reserved_current_bytes": 147750912,
    "device_memory_reserved_peak_bytes": 147750912,
    "device_type": "mps",
    "epoch": 25,
    "ram_current_bytes_end": 1207009280,
    "ram_current_bytes_start": 1194082304,
    "ram_peak_bytes_end": 1207107584,
    "wall_time_seconds": 20.17627199998242
  },
  {
    "cpu_time_seconds": 21.242300999999998,
    "device_memory_current_bytes": 62711552,
    "device_memory_peak_bytes": 62711552,
    "device_memory_reserved_current_bytes": 147750912,
    "device_memory_reserved_peak_bytes": 147750912,
    "device_type": "mps",
    "epoch": 26,
    "ram_current_bytes_end": 1220214784,
    "ram_current_bytes_start": 1207435264,
    "ram_peak_bytes_end": 1220313088,
    "wall_time_seconds": 20.152305499999784
  },
  {
    "cpu_time_seconds": 21.151933999999983,
    "device_memory_current_bytes": 62711552,
    "device_memory_peak_bytes": 62711552,
    "device_memory_reserved_current_bytes": 147750912,
    "device_memory_reserved_peak_bytes": 147750912,
    "device_type": "mps",
    "epoch": 27,
    "ram_current_bytes_end": 1233453056,
    "ram_current_bytes_start": 1220263936,
    "ram_peak_bytes_end": 1233551360,
    "wall_time_seconds": 20.019229083001846
  },
  {
    "cpu_time_seconds": 21.268574000000058,
    "device_memory_current_bytes": 62711552,
    "device_memory_peak_bytes": 62711552,
    "device_memory_reserved_current_bytes": 147750912,
    "device_memory_reserved_peak_bytes": 147750912,
    "device_type": "mps",
    "epoch": 28,
    "ram_current_bytes_end": 1247068160,
    "ram_current_bytes_start": 1233862656,
    "ram_peak_bytes_end": 1247150080,
    "wall_time_seconds": 20.154989833012223
  },
  {
    "cpu_time_seconds": 21.29629,
    "device_memory_current_bytes": 62711552,
    "device_memory_peak_bytes": 62711552,
    "device_memory_reserved_current_bytes": 147750912,
    "device_memory_reserved_peak_bytes": 147750912,
    "device_type": "mps",
    "epoch": 29,
    "ram_current_bytes_end": 1260371968,
    "ram_current_bytes_start": 1247363072,
    "ram_peak_bytes_end": 1260453888,
    "wall_time_seconds": 20.165287834010087
  },
  {
    "cpu_time_seconds": 21.24308899999994,
    "device_memory_current_bytes": 62711552,
    "device_memory_peak_bytes": 62711552,
    "device_memory_reserved_current_bytes": 147750912,
    "device_memory_reserved_peak_bytes": 147750912,
    "device_type": "mps",
    "epoch": 30,
    "ram_current_bytes_end": 1237352448,
    "ram_current_bytes_start": 1260601344,
    "ram_peak_bytes_end": 1267138560,
    "wall_time_seconds": 20.161327333014924
  },
  {
    "cpu_time_seconds": 21.28812300000004,
    "device_memory_current_bytes": 62711552,
    "device_memory_peak_bytes": 62711552,
    "device_memory_reserved_current_bytes": 147750912,
    "device_memory_reserved_peak_bytes": 147750912,
    "device_type": "mps",
    "epoch": 31,
    "ram_current_bytes_end": 1184710656,
    "ram_current_bytes_start": 1237417984,
    "ram_peak_bytes_end": 1267138560,
    "wall_time_seconds": 20.178381458012154
  },
  {
    "cpu_time_seconds": 21.369440000000054,
    "device_memory_current_bytes": 62711552,
    "device_memory_peak_bytes": 62711552,
    "device_memory_reserved_current_bytes": 147750912,
    "device_memory_reserved_peak_bytes": 147750912,
    "device_type": "mps",
    "epoch": 32,
    "ram_current_bytes_end": 1165737984,
    "ram_current_bytes_start": 1185185792,
    "ram_peak_bytes_end": 1267138560,
    "wall_time_seconds": 20.19888591702329
  },
  {
    "cpu_time_seconds": 21.264887000000044,
    "device_memory_current_bytes": 62711552,
    "device_memory_peak_bytes": 62711552,
    "device_memory_reserved_current_bytes": 147750912,
    "device_memory_reserved_peak_bytes": 147750912,
    "device_type": "mps",
    "epoch": 33,
    "ram_current_bytes_end": 1178959872,
    "ram_current_bytes_start": 1165950976,
    "ram_peak_bytes_end": 1267138560,
    "wall_time_seconds": 20.16115220799111
  },
  {
    "cpu_time_seconds": 21.17400400000008,
    "device_memory_current_bytes": 62711552,
    "device_memory_peak_bytes": 62711552,
    "device_memory_reserved_current_bytes": 147750912,
    "device_memory_reserved_peak_bytes": 147750912,
    "device_type": "mps",
    "epoch": 34,
    "ram_current_bytes_end": 1192148992,
    "ram_current_bytes_start": 1179025408,
    "ram_peak_bytes_end": 1267138560,
    "wall_time_seconds": 19.985280207998585
  },
  {
    "cpu_time_seconds": 21.245036000000027,
    "device_memory_current_bytes": 62711552,
    "device_memory_peak_bytes": 62711552,
    "device_memory_reserved_current_bytes": 147750912,
    "device_memory_reserved_peak_bytes": 147750912,
    "device_type": "mps",
    "epoch": 35,
    "ram_current_bytes_end": 1204797440,
    "ram_current_bytes_start": 1192673280,
    "ram_peak_bytes_end": 1267138560,
    "wall_time_seconds": 20.09593166600098
  },
  {
    "cpu_time_seconds": 21.254517999999962,
    "device_memory_current_bytes": 62711552,
    "device_memory_peak_bytes": 62711552,
    "device_memory_reserved_current_bytes": 147750912,
    "device_memory_reserved_peak_bytes": 147750912,
    "device_type": "mps",
    "epoch": 36,
    "ram_current_bytes_end": 1218019328,
    "ram_current_bytes_start": 1204862976,
    "ram_peak_bytes_end": 1267138560,
    "wall_time_seconds": 20.09094454202568
  },
  {
    "cpu_time_seconds": 21.178618999999912,
    "device_memory_current_bytes": 62711552,
    "device_memory_peak_bytes": 62711552,
    "device_memory_reserved_current_bytes": 147750912,
    "device_memory_reserved_peak_bytes": 147750912,
    "device_type": "mps",
    "epoch": 37,
    "ram_current_bytes_end": 1231470592,
    "ram_current_bytes_start": 1218084864,
    "ram_peak_bytes_end": 1267138560,
    "wall_time_seconds": 20.025719541008584
  },
  {
    "cpu_time_seconds": 21.312588000000005,
    "device_memory_current_bytes": 62711552,
    "device_memory_peak_bytes": 62711552,
    "device_memory_reserved_current_bytes": 147750912,
    "device_memory_reserved_peak_bytes": 147750912,
    "device_type": "mps",
    "epoch": 38,
    "ram_current_bytes_end": 1244479488,
    "ram_current_bytes_start": 1232158720,
    "ram_peak_bytes_end": 1267138560,
    "wall_time_seconds": 20.241610958008096
  },
  {
    "cpu_time_seconds": 21.330267999999933,
    "device_memory_current_bytes": 62711552,
    "device_memory_peak_bytes": 62711552,
    "device_memory_reserved_current_bytes": 147750912,
    "device_memory_reserved_peak_bytes": 147750912,
    "device_type": "mps",
    "epoch": 39,
    "ram_current_bytes_end": 1257734144,
    "ram_current_bytes_start": 1244545024,
    "ram_peak_bytes_end": 1267138560,
    "wall_time_seconds": 20.186654958000872
  },
  {
    "cpu_time_seconds": 21.252825999999914,
    "device_memory_current_bytes": 62711552,
    "device_memory_peak_bytes": 62711552,
    "device_memory_reserved_current_bytes": 147750912,
    "device_memory_reserved_peak_bytes": 147750912,
    "device_type": "mps",
    "epoch": 40,
    "ram_current_bytes_end": 1271660544,
    "ram_current_bytes_start": 1258143744,
    "ram_peak_bytes_end": 1271758848,
    "wall_time_seconds": 20.131875249993755
  },
  {
    "cpu_time_seconds": 21.188833000000045,
    "device_memory_current_bytes": 62711552,
    "device_memory_peak_bytes": 62711552,
    "device_memory_reserved_current_bytes": 147750912,
    "device_memory_reserved_peak_bytes": 147750912,
    "device_type": "mps",
    "epoch": 41,
    "ram_current_bytes_end": 1284800512,
    "ram_current_bytes_start": 1271824384,
    "ram_peak_bytes_end": 1284882432,
    "wall_time_seconds": 19.96126333301072
  },
  {
    "cpu_time_seconds": 21.317927000000054,
    "device_memory_current_bytes": 62711552,
    "device_memory_peak_bytes": 62711552,
    "device_memory_reserved_current_bytes": 147750912,
    "device_memory_reserved_peak_bytes": 147750912,
    "device_type": "mps",
    "epoch": 42,
    "ram_current_bytes_end": 1298399232,
    "ram_current_bytes_start": 1285242880,
    "ram_peak_bytes_end": 1298497536,
    "wall_time_seconds": 20.18742375000147
  },
  {
    "cpu_time_seconds": 21.316242999999986,
    "device_memory_current_bytes": 62711552,
    "device_memory_peak_bytes": 62711552,
    "device_memory_reserved_current_bytes": 147750912,
    "device_memory_reserved_peak_bytes": 147750912,
    "device_type": "mps",
    "epoch": 43,
    "ram_current_bytes_end": 1311866880,
    "ram_current_bytes_start": 1298677760,
    "ram_peak_bytes_end": 1311965184,
    "wall_time_seconds": 20.22282633400755
  },
  {
    "cpu_time_seconds": 21.173477999999932,
    "device_memory_current_bytes": 62711552,
    "device_memory_peak_bytes": 62711552,
    "device_memory_reserved_current_bytes": 147750912,
    "device_memory_reserved_peak_bytes": 147750912,
    "device_type": "mps",
    "epoch": 44,
    "ram_current_bytes_end": 1325203456,
    "ram_current_bytes_start": 1311916032,
    "ram_peak_bytes_end": 1325285376,
    "wall_time_seconds": 20.07238112500636
  },
  {
    "cpu_time_seconds": 21.538888999999926,
    "device_memory_current_bytes": 62711552,
    "device_memory_peak_bytes": 62711552,
    "device_memory_reserved_current_bytes": 147750912,
    "device_memory_reserved_peak_bytes": 147750912,
    "device_type": "mps",
    "epoch": 45,
    "ram_current_bytes_end": 1051099136,
    "ram_current_bytes_start": 1325662208,
    "ram_peak_bytes_end": 1337671680,
    "wall_time_seconds": 20.29663483297918
  },
  {
    "cpu_time_seconds": 21.46705600000007,
    "device_memory_current_bytes": 62711552,
    "device_memory_peak_bytes": 62711552,
    "device_memory_reserved_current_bytes": 147750912,
    "device_memory_reserved_peak_bytes": 147750912,
    "device_type": "mps",
    "epoch": 46,
    "ram_current_bytes_end": 1067417600,
    "ram_current_bytes_start": 1054572544,
    "ram_peak_bytes_end": 1337671680,
    "wall_time_seconds": 20.306132415978936
  },
  {
    "cpu_time_seconds": 21.21929399999999,
    "device_memory_current_bytes": 62711552,
    "device_memory_peak_bytes": 62711552,
    "device_memory_reserved_current_bytes": 147750912,
    "device_memory_reserved_peak_bytes": 147750912,
    "device_type": "mps",
    "epoch": 47,
    "ram_current_bytes_end": 1080868864,
    "ram_current_bytes_start": 1067548672,
    "ram_peak_bytes_end": 1337671680,
    "wall_time_seconds": 20.123958000011044
  },
  {
    "cpu_time_seconds": 21.150303000000008,
    "device_memory_current_bytes": 62711552,
    "device_memory_peak_bytes": 62711552,
    "device_memory_reserved_current_bytes": 147750912,
    "device_memory_reserved_peak_bytes": 147750912,
    "device_type": "mps",
    "epoch": 48,
    "ram_current_bytes_end": 1094172672,
    "ram_current_bytes_start": 1080934400,
    "ram_peak_bytes_end": 1337671680,
    "wall_time_seconds": 20.04122737501166
  },
  {
    "cpu_time_seconds": 21.261087999999972,
    "device_memory_current_bytes": 62711552,
    "device_memory_peak_bytes": 62711552,
    "device_memory_reserved_current_bytes": 147750912,
    "device_memory_reserved_peak_bytes": 147750912,
    "device_type": "mps",
    "epoch": 49,
    "ram_current_bytes_end": 1092993024,
    "ram_current_bytes_start": 1094696960,
    "ram_peak_bytes_end": 1337671680,
    "wall_time_seconds": 20.24340120801935
  },
  {
    "cpu_time_seconds": 21.309131999999863,
    "device_memory_current_bytes": 62711552,
    "device_memory_peak_bytes": 62711552,
    "device_memory_reserved_current_bytes": 147750912,
    "device_memory_reserved_peak_bytes": 147750912,
    "device_type": "mps",
    "epoch": 50,
    "ram_current_bytes_end": 1107001344,
    "ram_current_bytes_start": 1094205440,
    "ram_peak_bytes_end": 1337671680,
    "wall_time_seconds": 20.196269707987085
  },
  {
    "cpu_time_seconds": 21.17143299999998,
    "device_memory_current_bytes": 62711552,
    "device_memory_peak_bytes": 62711552,
    "device_memory_reserved_current_bytes": 147750912,
    "device_memory_reserved_peak_bytes": 147750912,
    "device_type": "mps",
    "epoch": 51,
    "ram_current_bytes_end": 1120665600,
    "ram_current_bytes_start": 1107066880,
    "ram_peak_bytes_end": 1337671680,
    "wall_time_seconds": 20.041999959008535
  },
  {
    "cpu_time_seconds": 21.248514000000114,
    "device_memory_current_bytes": 62711552,
    "device_memory_peak_bytes": 62711552,
    "device_memory_reserved_current_bytes": 147750912,
    "device_memory_reserved_peak_bytes": 147750912,
    "device_type": "mps",
    "epoch": 52,
    "ram_current_bytes_end": 1133903872,
    "ram_current_bytes_start": 1120714752,
    "ram_peak_bytes_end": 1337671680,
    "wall_time_seconds": 20.10425191599643
  },
  {
    "cpu_time_seconds": 21.345649000000094,
    "device_memory_current_bytes": 62711552,
    "device_memory_peak_bytes": 62711552,
    "device_memory_reserved_current_bytes": 147750912,
    "device_memory_reserved_peak_bytes": 147750912,
    "device_type": "mps",
    "epoch": 53,
    "ram_current_bytes_end": 1148878848,
    "ram_current_bytes_start": 1135984640,
    "ram_peak_bytes_end": 1337671680,
    "wall_time_seconds": 20.22005995802465
  },
  {
    "cpu_time_seconds": 21.33523500000001,
    "device_memory_current_bytes": 62711552,
    "device_memory_peak_bytes": 62711552,
    "device_memory_reserved_current_bytes": 147750912,
    "device_memory_reserved_peak_bytes": 147750912,
    "device_type": "mps",
    "epoch": 54,
    "ram_current_bytes_end": 1162838016,
    "ram_current_bytes_start": 1148977152,
    "ram_peak_bytes_end": 1337671680,
    "wall_time_seconds": 20.14360758298426
  },
  {
    "cpu_time_seconds": 21.31774100000007,
    "device_memory_current_bytes": 62711552,
    "device_memory_peak_bytes": 62711552,
    "device_memory_reserved_current_bytes": 147750912,
    "device_memory_reserved_peak_bytes": 147750912,
    "device_type": "mps",
    "epoch": 55,
    "ram_current_bytes_end": 1176879104,
    "ram_current_bytes_start": 1163214848,
    "ram_peak_bytes_end": 1337671680,
    "wall_time_seconds": 20.20900483301375
  },
  {
    "cpu_time_seconds": 21.502502999999933,
    "device_memory_current_bytes": 62711552,
    "device_memory_peak_bytes": 62711552,
    "device_memory_reserved_current_bytes": 147750912,
    "device_memory_reserved_peak_bytes": 147750912,
    "device_type": "mps",
    "epoch": 56,
    "ram_current_bytes_end": 1190215680,
    "ram_current_bytes_start": 1176944640,
    "ram_peak_bytes_end": 1337671680,
    "wall_time_seconds": 20.277335499995388
  },
  {
    "cpu_time_seconds": 21.296190000000024,
    "device_memory_current_bytes": 62711552,
    "device_memory_peak_bytes": 62711552,
    "device_memory_reserved_current_bytes": 147750912,
    "device_memory_reserved_peak_bytes": 147750912,
    "device_type": "mps",
    "epoch": 57,
    "ram_current_bytes_end": 1147371520,
    "ram_current_bytes_start": 1190248448,
    "ram_peak_bytes_end": 1337671680,
    "wall_time_seconds": 20.1694365410076
  },
  {
    "cpu_time_seconds": 21.21927699999992,
    "device_memory_current_bytes": 62711552,
    "device_memory_peak_bytes": 62711552,
    "device_memory_reserved_current_bytes": 147750912,
    "device_memory_reserved_peak_bytes": 147750912,
    "device_type": "mps",
    "epoch": 58,
    "ram_current_bytes_end": 1006501888,
    "ram_current_bytes_start": 1147879424,
    "ram_peak_bytes_end": 1337671680,
    "wall_time_seconds": 20.078720958990743
  },
  {
    "cpu_time_seconds": 21.265290999999934,
    "device_memory_current_bytes": 62711552,
    "device_memory_peak_bytes": 62711552,
    "device_memory_reserved_current_bytes": 147750912,
    "device_memory_reserved_peak_bytes": 147750912,
    "device_type": "mps",
    "epoch": 59,
    "ram_current_bytes_end": 781320192,
    "ram_current_bytes_start": 891912192,
    "ram_peak_bytes_end": 1337671680,
    "wall_time_seconds": 20.1873220000125
  },
  {
    "cpu_time_seconds": 21.28801199999998,
    "device_memory_current_bytes": 62711552,
    "device_memory_peak_bytes": 62711552,
    "device_memory_reserved_current_bytes": 147750912,
    "device_memory_reserved_peak_bytes": 147750912,
    "device_type": "mps",
    "epoch": 60,
    "ram_current_bytes_end": 765116416,
    "ram_current_bytes_start": 782794752,
    "ram_peak_bytes_end": 1337671680,
    "wall_time_seconds": 20.1438937500061
  }
]
